CHANGES
LICENSE
MANIFEST.in
README.rst
setup.py
bottle_utils/__init__.py
bottle_utils/ajax.py
bottle_utils/common.py
bottle_utils/csrf.py
bottle_utils/flash.py
bottle_utils/html.py
bottle_utils/http.py
bottle_utils/i18n.py
bottle_utils/lazy.py
bottle_utils/meta.py
bottle_utils.egg-info/PKG-INFO
bottle_utils.egg-info/SOURCES.txt
bottle_utils.egg-info/dependency_links.txt
bottle_utils.egg-info/requires.txt
bottle_utils.egg-info/top_level.txt
bottle_utils/form/__init__.py
bottle_utils/form/exceptions.py
bottle_utils/form/fields.py
bottle_utils/form/forms.py
bottle_utils/form/validators.py